CHANGES.txt
DEPENDENCES.txt
README.txt
setup.py
src/nd/__init__.py
src/nd.semanticcore.egg-info/PKG-INFO
src/nd.semanticcore.egg-info/SOURCES.txt
src/nd.semanticcore.egg-info/dependency_links.txt
src/nd.semanticcore.egg-info/entry_points.txt
src/nd.semanticcore.egg-info/namespace_packages.txt
src/nd.semanticcore.egg-info/not-zip-safe
src/nd.semanticcore.egg-info/requires.txt
src/nd.semanticcore.egg-info/top_level.txt
src/nd/semanticcore/__init__.py
src/nd/semanticcore/average.py
src/nd/semanticcore/cloudcompare.py
src/nd/semanticcore/nd.semanticcore.txt
src/nd/semanticcore/semanticcore.py
src/nd/semanticcore/text2vector.py
src/nd/semanticcore/tfidf.py
src/nd/semanticcore/vectorcompare.py